program/__init__.py
kalkulator_bmi-0.0.1.dist-info/LICENSE
kalkulator_bmi-0.0.1.dist-info/METADATA
kalkulator_bmi-0.0.1.dist-info/WHEEL
kalkulator_bmi-0.0.1.dist-info/top_level.txt
kalkulator_bmi-0.0.1.dist-info/RECORD
