Metadata-Version: 2.1
Name: kalkulator-bmi
Version: 0.0.1
Summary: Paket ini berisi kalkulator yang berfungsi untuk menghitung BMI atau IMT
Home-page: https://github.com/Miqbal20/kalkulator_bmi
Author: Muhammad Iqbal
Author-email: Muhammad Iqbal <miqbal020@hotmail.com>
Project-URL: Homepage, https://github.com/Miqbal20/kalkulator_bmi
Project-URL: Bug Tracker, https://github.com/Miqbal20/kalkulator_bmi/issues
Classifier: Programming Language :: Python :: 3
Classifier: License :: OSI Approved :: MIT License
Classifier: Operating System :: OS Independent
Classifier: Development Status :: 4 - Beta
Requires-Python: >=3.7
License-File: LICENSE
